{
  "hash": "e3774fa4",
  "browserHash": "95f4c460",
  "optimized": {
    "react": {
      "src": "../../node_modules/react/index.js",
      "file": "react.js",
      "fileHash": "2f9dad44",
      "needsInterop": true
    },
    "react-dom/client": {
      "src": "../../node_modules/react-dom/client.js",
      "file": "react-dom_client.js",
      "fileHash": "b4ac714c",
      "needsInterop": true
    },
    "@reduxjs/toolkit": {
      "src": "../../node_modules/@reduxjs/toolkit/dist/redux-toolkit.esm.js",
      "file": "@reduxjs_toolkit.js",
      "fileHash": "70d38952",
      "needsInterop": false
    },
    "react-redux": {
      "src": "../../node_modules/react-redux/es/index.js",
      "file": "react-redux.js",
      "fileHash": "af6ea5c9",
      "needsInterop": false
    },
    "react-router-dom": {
      "src": "../../node_modules/react-router-dom/dist/index.js",
      "file": "react-router-dom.js",
      "fileHash": "961d885c",
      "needsInterop": false
    },
    "@mui/material": {
      "src": "../../node_modules/@mui/material/index.js",
      "file": "@mui_material.js",
      "fileHash": "886b1e9f",
      "needsInterop": false
    },
    "react-hook-form": {
      "src": "../../node_modules/react-hook-form/dist/index.esm.mjs",
      "file": "react-hook-form.js",
      "fileHash": "40eb4618",
      "needsInterop": false
    },
    "@hookform/resolvers/yup": {
      "src": "../../node_modules/@hookform/resolvers/yup/dist/yup.mjs",
      "file": "@hookform_resolvers_yup.js",
      "fileHash": "7e7501bf",
      "needsInterop": false
    },
    "yup": {
      "src": "../../node_modules/yup/index.esm.js",
      "file": "yup.js",
      "fileHash": "76d1669c",
      "needsInterop": false
    },
    "@mui/material/AppBar": {
      "src": "../../node_modules/@mui/material/AppBar/index.js",
      "file": "@mui_material_AppBar.js",
      "fileHash": "bdb38550",
      "needsInterop": false
    },
    "@mui/material/Box": {
      "src": "../../node_modules/@mui/material/Box/index.js",
      "file": "@mui_material_Box.js",
      "fileHash": "4f692c3c",
      "needsInterop": false
    },
    "@mui/material/Toolbar": {
      "src": "../../node_modules/@mui/material/Toolbar/index.js",
      "file": "@mui_material_Toolbar.js",
      "fileHash": "c889b4da",
      "needsInterop": false
    },
    "@mui/material/Typography": {
      "src": "../../node_modules/@mui/material/Typography/index.js",
      "file": "@mui_material_Typography.js",
      "fileHash": "9d4a53b2",
      "needsInterop": false
    },
    "@mui/material/IconButton": {
      "src": "../../node_modules/@mui/material/IconButton/index.js",
      "file": "@mui_material_IconButton.js",
      "fileHash": "29797120",
      "needsInterop": false
    },
    "@mui/icons-material/Menu": {
      "src": "../../node_modules/@mui/icons-material/Menu.js",
      "file": "@mui_icons-material_Menu.js",
      "fileHash": "31d07428",
      "needsInterop": true
    },
    "@mui/material/Container": {
      "src": "../../node_modules/@mui/material/Container/index.js",
      "file": "@mui_material_Container.js",
      "fileHash": "cd798893",
      "needsInterop": false
    },
    "@mui/material/Link": {
      "src": "../../node_modules/@mui/material/Link/index.js",
      "file": "@mui_material_Link.js",
      "fileHash": "6de99e1e",
      "needsInterop": false
    }
  },
  "chunks": {
    "chunk-B2WIWPQT": {
      "file": "chunk-B2WIWPQT.js"
    },
    "chunk-WPVVMC5B": {
      "file": "chunk-WPVVMC5B.js"
    },
    "chunk-3NDRUOYO": {
      "file": "chunk-3NDRUOYO.js"
    },
    "chunk-I7GIZIJC": {
      "file": "chunk-I7GIZIJC.js"
    },
    "chunk-2IWJKDPD": {
      "file": "chunk-2IWJKDPD.js"
    },
    "chunk-VJXXAH5B": {
      "file": "chunk-VJXXAH5B.js"
    },
    "chunk-IHSKWTTM": {
      "file": "chunk-IHSKWTTM.js"
    },
    "chunk-BNJRYFP2": {
      "file": "chunk-BNJRYFP2.js"
    },
    "chunk-C4KG2XDU": {
      "file": "chunk-C4KG2XDU.js"
    },
    "chunk-ZZYTY3PR": {
      "file": "chunk-ZZYTY3PR.js"
    },
    "chunk-XRCIVST5": {
      "file": "chunk-XRCIVST5.js"
    },
    "chunk-NLJYPKFE": {
      "file": "chunk-NLJYPKFE.js"
    },
    "chunk-RJTR4JAV": {
      "file": "chunk-RJTR4JAV.js"
    },
    "chunk-2UWNGZ6G": {
      "file": "chunk-2UWNGZ6G.js"
    },
    "chunk-6GNJQVVF": {
      "file": "chunk-6GNJQVVF.js"
    },
    "chunk-OTY6O57J": {
      "file": "chunk-OTY6O57J.js"
    },
    "chunk-PGK7FCXT": {
      "file": "chunk-PGK7FCXT.js"
    },
    "chunk-2PA4WPI3": {
      "file": "chunk-2PA4WPI3.js"
    },
    "chunk-ROME4SDB": {
      "file": "chunk-ROME4SDB.js"
    }
  }
}